trio_mongodb/__init__.py
trio_mongodb/process.py
trio_mongodb/threads.py
trio_mongodb-0.5.0.dist-info/LICENSE
trio_mongodb-0.5.0.dist-info/METADATA
trio_mongodb-0.5.0.dist-info/WHEEL
trio_mongodb-0.5.0.dist-info/top_level.txt
trio_mongodb-0.5.0.dist-info/RECORD
