Metadata-Version: 2.1
Name: trio_mongodb
Version: 0.5.0
Summary: Trio pymongo wrapper for async operations using threads or processes.
Home-page: https://github.com/obnoxiousish/trio_mongodb
Author: obnoxious
Author-email: obnoxious@dongcorp.org
Classifier: Programming Language :: Python :: 3
Classifier: License :: OSI Approved :: GNU General Public License v3 (GPLv3)
Classifier: Operating System :: OS Independent
Requires-Python: >=3.8
License-File: LICENSE
Requires-Dist: trio
Requires-Dist: pymongo
Requires-Dist: hypercorn
Requires-Dist: httpx
Requires-Dist: starlette
